nasdaq_news/__init__.py
nasdaq_news/fetcher.py
nasdaq_news/data/AAPL.json
nasdaq_news/data/ADBE.json
nasdaq_news/data/ADI.json
nasdaq_news/data/ADP.json
nasdaq_news/data/AEP.json
nasdaq_news/data/AKAM.json
nasdaq_news/data/ALGN.json
nasdaq_news/data/AMGN.json
nasdaq_news/data/AMZN.json
nasdaq_news/data/ANSS.json
nasdaq_news/data/ASML.json
nasdaq_news/data/AVGO.json
nasdaq_news/data/BIIB.json
nasdaq_news/data/BKNG.json
nasdaq_news/data/BKR.json
nasdaq_news/data/CDNS.json
nasdaq_news/data/CDW.json
nasdaq_news/data/CEG.json
nasdaq_news/data/CHTR.json
nasdaq_news/data/CMCSA.json
nasdaq_news/data/COST.json
nasdaq_news/data/CPRT.json
nasdaq_news/data/CRWD.json
nasdaq_news/data/CSCO.json
nasdaq_news/data/CTAS.json
nasdaq_news/data/CTSH.json
nasdaq_news/data/DLTR.json
nasdaq_news/data/DXCM.json
nasdaq_news/data/EA.json
nasdaq_news/data/ENPH.json
nasdaq_news/data/EXC.json
nasdaq_news/data/EXPE.json
nasdaq_news/data/FANG.json
nasdaq_news/data/FAST.json
nasdaq_news/data/FOX.json
nasdaq_news/data/FOXA.json
nasdaq_news/data/FTNT.json
nasdaq_news/data/GILD.json
nasdaq_news/data/GOOG.json
nasdaq_news/data/HBAN.json
nasdaq_news/data/IDXX.json
nasdaq_news/data/ILMN.json
nasdaq_news/data/INCY.json
nasdaq_news/data/INTC.json
nasdaq_news/data/INTU.json
nasdaq_news/data/ISRG.json
nasdaq_news/data/JBHT.json
nasdaq_news/data/KHC.json
nasdaq_news/data/KLAC.json
nasdaq_news/data/LCID.json
nasdaq_news/data/LRCX.json
nasdaq_news/data/LULU.json
nasdaq_news/data/MAR.json
nasdaq_news/data/MDLZ.json
nasdaq_news/data/META.json
nasdaq_news/data/MNST.json
nasdaq_news/data/MRNA.json
nasdaq_news/data/MSFT.json
nasdaq_news/data/MTCH.json
nasdaq_news/data/MU.json
nasdaq_news/data/NDAQ.json
nasdaq_news/data/NFLX.json
nasdaq_news/data/NLOK.json
nasdaq_news/data/NVDA.json
nasdaq_news/data/NXPI.json
nasdaq_news/data/OKTA.json
nasdaq_news/data/ORLY.json
nasdaq_news/data/PANW.json
nasdaq_news/data/PAYX.json
nasdaq_news/data/PCAR.json
nasdaq_news/data/PDD.json
nasdaq_news/data/PEP.json
nasdaq_news-0.1.1.dist-info/LICENSE.txt
nasdaq_news-0.1.1.dist-info/METADATA
nasdaq_news-0.1.1.dist-info/WHEEL
nasdaq_news-0.1.1.dist-info/top_level.txt
nasdaq_news-0.1.1.dist-info/RECORD
