Metadata-Version: 2.1
Name: nasdaq-news
Version: 0.1.1
Summary: Python package to fetch NASDAQ-100 stock news from FMP API
Author: Your Name
Author-email: Shekhar Biswas <shekhar07.nitdgp@gmail.com>
Project-URL: Homepage, https://github.com/shekharbiswas/nasdaq_news
Project-URL: Repository, https://github.com/shekharbiswas/nasdaq_news
Requires-Python: >=3.7
License-File: LICENSE.txt
Requires-Dist: requests
Requires-Dist: pandas
